[{"Gjilan Municipality":""},{"Istog Municipality":""},{"Komuna e Artanës":""},{"Komuna e Dardanës":""},{"Komuna e Deçanit":""},{"Komuna e Drenasit":""},{"Komuna e Ferizajit":""},{"Komuna e Fushë Kosovës":""},{"Komuna e Gjakovës":""},{"Komuna e Hani i Elezit":""},{"Komuna e Junikut":""},{"Komuna e Kaçanikut":""},{"Komuna e Klinës":""},{"Komuna e Leposaviqit":""},{"Komuna e Lipjanit":""},{"Komuna e Malishevës":""},{"Komuna e Mamushes":""},{"Komuna e Mitrovicës":""},{"Komuna e Obiliqit":""},{"Komuna e Pejës":""},{"Komuna e Prizrenit":""},{"Komuna e Rahovecit":""},{"Komuna e Sharrit":""},{"Komuna e Shtërpcës":""},{"Komuna e Shtimes":""},{"Komuna e Skënderajt":""},{"Komuna e Therandës":""},{"Komuna e Vitisë":""},{"Komuna e Vushtrrisë":""},{"Komuna e Zubin Potokut":""},{"Komuna e Zvecanit":""},{"Podujevo Municipality":""},{"Prishtina Municipality":""}]